ribbitxdb/__init__.py
ribbitxdb/async_connection.py
ribbitxdb/connection.py
ribbitxdb/cursor.py
ribbitxdb/advanced/__init__.py
ribbitxdb/advanced/cte.py
ribbitxdb/advanced/subqueries.py
ribbitxdb/advanced/window_functions.py
ribbitxdb/auth/__init__.py
ribbitxdb/auth/authenticator.py
ribbitxdb/auth/authorizer.py
ribbitxdb/auth/user_manager.py
ribbitxdb/backup/__init__.py
ribbitxdb/backup/backup.py
ribbitxdb/backup/restore.py
ribbitxdb/batch/__init__.py
ribbitxdb/batch/operations.py
ribbitxdb/client/__init__.py
ribbitxdb/client/network_client.py
ribbitxdb/index/__init__.py
ribbitxdb/index/btree.py
ribbitxdb/index/manager.py
ribbitxdb/migrations/__init__.py
ribbitxdb/migrations/manager.py
ribbitxdb/pool/__init__.py
ribbitxdb/pool/connection_pool.py
ribbitxdb/query/__init__.py
ribbitxdb/query/executor.py
ribbitxdb/query/optimizer.py
ribbitxdb/query/parser.py
ribbitxdb/replication/__init__.py
ribbitxdb/replication/wal.py
ribbitxdb/schema/__init__.py
ribbitxdb/schema/metadata.py
ribbitxdb/schema/system_tables.py
ribbitxdb/schema/types.py
ribbitxdb/security/__init__.py
ribbitxdb/security/encryption.py
ribbitxdb/security/hasher.py
ribbitxdb/server/__init__.py
ribbitxdb/server/cli.py
ribbitxdb/server/protocol.py
ribbitxdb/server/session.py
ribbitxdb/server/tcp_server.py
ribbitxdb/storage/__init__.py
ribbitxdb/storage/compressor.py
ribbitxdb/storage/engine.py
ribbitxdb/storage/page.py
ribbitxdb/transaction/__init__.py
ribbitxdb/transaction/manager.py
ribbitxdb/utils/__init__.py
ribbitxdb/utils/constants.py
ribbitxdb/utils/exceptions.py
ribbitxdb-1.1.8.dist-info/licenses/LICENSE
ribbitxdb-1.1.8.dist-info/METADATA
ribbitxdb-1.1.8.dist-info/WHEEL
ribbitxdb-1.1.8.dist-info/entry_points.txt
ribbitxdb-1.1.8.dist-info/top_level.txt
ribbitxdb-1.1.8.dist-info/RECORD
