Metadata-Version: 2.4
Name: ribbitxdb
Version: 1.1.8
Summary: Drop-in SQLite alternative with async API, migrations, schema introspection, and 100% SQL compatibility
Home-page: https://ribbitx.com
Author: RibbitX Team
Author-email: contact@ribbitx.com
Project-URL: Homepage, https://ribbitx.com
Project-URL: Bug Reports, https://github.com/ribbitx/ribbitxdb
Project-URL: Source, https://github.com/ribbitx/ribbitxdb
Project-URL: Documentation, https://docs.ribbitx.com
Keywords: database,production,stable,sql,client-server,tls,authentication,replication,connection-pool,blake2,lzma,compression,security,lightweight,embedded
Classifier: Development Status :: 5 - Production/Stable
Classifier: Intended Audience :: Developers
Classifier: Topic :: Database
Classifier: Topic :: Database :: Database Engines/Servers
Classifier: Topic :: Software Development :: Libraries :: Python Modules
Classifier: Topic :: Security :: Cryptography
Classifier: Topic :: System :: Networking
Classifier: License :: OSI Approved :: MIT License
Classifier: Programming Language :: Python :: 3
Classifier: Programming Language :: Python :: 3.8
Classifier: Programming Language :: Python :: 3.9
Classifier: Programming Language :: Python :: 3.10
Classifier: Programming Language :: Python :: 3.11
Classifier: Programming Language :: Python :: 3.12
Classifier: Programming Language :: Python :: 3.13
Classifier: Operating System :: OS Independent
Classifier: Operating System :: Microsoft :: Windows
Classifier: Operating System :: POSIX :: Linux
Classifier: Operating System :: MacOS
Requires-Python: >=3.8
License-File: LICENSE
Provides-Extra: dev
Requires-Dist: pytest>=7.0.0; extra == "dev"
Requires-Dist: pytest-cov>=4.0.0; extra == "dev"
Provides-Extra: server
Dynamic: author
Dynamic: author-email
Dynamic: classifier
Dynamic: description
Dynamic: description-content-type
Dynamic: home-page
Dynamic: keywords
Dynamic: license-file
Dynamic: project-url
Dynamic: provides-extra
Dynamic: requires-python
Dynamic: summary
